.coveragerc
.editorconfig
.gitignore
.travis.yml
CHANGES.rst
CONTRIBUTORS.rst
MANIFEST.in
README.rst
bootstrap-buildout.py
buildout.cfg
setup.py
travis.cfg
buildout.d/base.cfg
buildout.d/checkouts.cfg
buildout.d/development.cfg
buildout.d/jenkins.cfg
buildout.d/sources.cfg
buildout.d/versions.cfg
docs/LICENSE.GPL
docs/LICENSE.rst
src/ps/__init__.py
src/ps.plone.jssor.egg-info/PKG-INFO
src/ps.plone.jssor.egg-info/SOURCES.txt
src/ps.plone.jssor.egg-info/dependency_links.txt
src/ps.plone.jssor.egg-info/entry_points.txt
src/ps.plone.jssor.egg-info/namespace_packages.txt
src/ps.plone.jssor.egg-info/not-zip-safe
src/ps.plone.jssor.egg-info/requires.txt
src/ps.plone.jssor.egg-info/top_level.txt
src/ps/plone/__init__.py
src/ps/plone/jssor/__init__.py
src/ps/plone/jssor/configure.zcml
src/ps/plone/jssor/migration.py
src/ps/plone/jssor/setuphandlers.py
src/ps/plone/jssor/testing.py
src/ps/plone/jssor/browser/__init__.py
src/ps/plone/jssor/browser/configure.zcml
src/ps/plone/jssor/browser/interfaces.py
src/ps/plone/jssor/browser/slider.py
src/ps/plone/jssor/browser/overrides/.gitkeep
src/ps/plone/jssor/browser/static/.gitkeep
src/ps/plone/jssor/browser/static/a01.png
src/ps/plone/jssor/browser/static/a02.png
src/ps/plone/jssor/browser/static/a03.png
src/ps/plone/jssor/browser/static/a04.png
src/ps/plone/jssor/browser/static/a06.png
src/ps/plone/jssor/browser/static/a07.png
src/ps/plone/jssor/browser/static/a08.png
src/ps/plone/jssor/browser/static/a09.png
src/ps/plone/jssor/browser/static/a10.png
src/ps/plone/jssor/browser/static/a11.png
src/ps/plone/jssor/browser/static/a12.png
src/ps/plone/jssor/browser/static/a13.png
src/ps/plone/jssor/browser/static/a14.png
src/ps/plone/jssor/browser/static/a15.png
src/ps/plone/jssor/browser/static/a16.png
src/ps/plone/jssor/browser/static/a17.png
src/ps/plone/jssor/browser/static/a18.png
src/ps/plone/jssor/browser/static/a19.png
src/ps/plone/jssor/browser/static/a20.png
src/ps/plone/jssor/browser/static/a21.png
src/ps/plone/jssor/browser/static/b02.png
src/ps/plone/jssor/browser/static/b03.png
src/ps/plone/jssor/browser/static/b05.png
src/ps/plone/jssor/browser/static/b06.png
src/ps/plone/jssor/browser/static/b07.png
src/ps/plone/jssor/browser/static/b10.png
src/ps/plone/jssor/browser/static/b11.png
src/ps/plone/jssor/browser/static/b12.png
