Metadata-Version: 1.0
Name: ps.plone.jssor
Version: 0.3
Summary: Configurable Jssor Slider to show propertyshelf MLS Listings
Home-page: http://pypi.python.org/pypi/ps.plone.jssor
Author: Propertyshelf, Inc.
Author-email: development@propertyshelf.com
License: GPL
Keywords: Plone Jssor Slider
Platform: UNKNOWN
Classifier: Environment :: Web Environment
Classifier: Framework :: Plone
Classifier: Framework :: Plone :: 4.3
Classifier: Programming Language :: Python
Classifier: Programming Language :: Python :: 2.7
